exsum/__init__.py
exsum/gui_server.py
exsum/run_server.py
exsum/static/bootstrap.bundle.min.js
exsum/static/bootstrap.css
exsum/static/favicon.ico
exsum/static/jquery.min.js
exsum/static/plotly-2.4.2.min.js
exsum/templates/auto_tune_modal.html
exsum/templates/blocking_modal.html
exsum/templates/control_buttons.html
exsum/templates/feu_vis.html
exsum/templates/feu_vis_buttons.html
exsum/templates/index.html
exsum/templates/metric_plot.html
exsum/templates/metric_table.html
exsum/templates/no_rule_selected_modal.html
exsum/templates/param_out_of_range_modal.html
exsum/templates/parameter_sliders.html
exsum/templates/rule_buttons.html
exsum/templates/rule_formula.html
exsum/templates/sentence_vis.html
exsum/templates/sentence_vis_buttons.html
exsum/templates/vis_modals.html
exsum-1.0.0.dist-info/LICENSE
exsum-1.0.0.dist-info/METADATA
exsum-1.0.0.dist-info/WHEEL
exsum-1.0.0.dist-info/entry_points.txt
exsum-1.0.0.dist-info/top_level.txt
exsum-1.0.0.dist-info/RECORD
