Metadata-Version: 2.1
Name: exsum
Version: 1.0.0
Summary: Explanation Summary (ExSum)
Home-page: https://yilunzhou.github.io/exsum/
Author: Yilun Zhou
Author-email: zyilun94@gmail.com
License: MIT
Keywords: interpretability,natural language processing,machine learning
Platform: UNKNOWN
Classifier: Development Status :: 5 - Production/Stable
Classifier: Framework :: Flask
Classifier: Intended Audience :: Science/Research
Classifier: Topic :: Scientific/Engineering :: Artificial Intelligence
Classifier: License :: OSI Approved :: MIT License
Classifier: Programming Language :: Python
License-File: LICENSE
Requires-Dist: dill
Requires-Dist: Flask
Requires-Dist: numpy
Requires-Dist: scipy
Requires-Dist: tqdm
